mex/__init__.py
mex/release/__init__.py
mex/release/cli.py
mex/release/emoji.py
mex/release/release.py
mex/release/sign.py
mex_release-1.0.0.dist-info/METADATA
mex_release-1.0.0.dist-info/WHEEL
mex_release-1.0.0.dist-info/entry_points.txt
mex_release-1.0.0.dist-info/licenses/LICENSE
mex_release-1.0.0.dist-info/RECORD
