Metadata-Version: 2.1
Name: mex-release
Version: 1.0.0
Summary: Release tools for the RKI MEx project.
Author-Email: MEx Team <mex@rki.de>
License: MIT License
Project-URL: Repository, https://github.com/robert-koch-institut/mex-release
Requires-Python: <3.12,>=3.11
Requires-Dist: typer>=0.20.0
Requires-Dist: tomlkit>=0.13.3
Provides-Extra: dev
Requires-Dist: ipdb>=0.13; extra == "dev"
Requires-Dist: mypy>=1; extra == "dev"
Requires-Dist: ruff>=0.14; extra == "dev"
